cybersec_sdk/__init__.py
cybersec_sdk/ai_assistant.py
cybersec_sdk/analyzer.py
cybersec_sdk/external_data.py
cybersec_sdk/graph_manager.py
cybersec_sdk/ml_models.py
cybersec_sdk/neo4j_manager.py
cybersec_sdk/reporting.py
cybersec_sdk/ui.py
cyberguard_sdk-1.0.0.dist-info/METADATA
cyberguard_sdk-1.0.0.dist-info/WHEEL
cyberguard_sdk-1.0.0.dist-info/entry_points.txt
cyberguard_sdk-1.0.0.dist-info/top_level.txt
cyberguard_sdk-1.0.0.dist-info/RECORD
